dnbc4tools/__init__.py
dnbc4tools/dnbc4tools.py
dnbc4tools/atac/__init__.py
dnbc4tools/atac/analysis.py
dnbc4tools/atac/data.py
dnbc4tools/atac/decon.py
dnbc4tools/atac/dnbc4atac.py
dnbc4tools/atac/mkref.py
dnbc4tools/atac/multi.py
dnbc4tools/atac/report.py
dnbc4tools/atac/run.py
dnbc4tools/atac/src/Cluster_signac.R
dnbc4tools/atac/src/__init__.py
dnbc4tools/atac/src/calculate_jaccardindex.so
dnbc4tools/atac/src/filter_qc.so
dnbc4tools/atac/src/generate_report.so
dnbc4tools/atac/src/scanpy_cluster.so
dnbc4tools/config/atac/whitelist_atac.txt.gz
dnbc4tools/config/blacklist/hg19.full.blacklist.bed
dnbc4tools/config/blacklist/hg38.full.blacklist.bed
dnbc4tools/config/blacklist/mm10.full.blacklist.bed
dnbc4tools/config/cellbarcode/oligo_type.json
dnbc4tools/config/cellbarcode/oligo_type.txt
dnbc4tools/config/cellbarcode/scRNA_beads_darkReaction.json
dnbc4tools/config/cellbarcode/scRNA_oligo_R2_noDarkReaction.json
dnbc4tools/config/cellbarcode/scRNA_oligo_darkReaction.json
dnbc4tools/config/cellbarcode/scRNA5Pv1/scRNA_beads_v1.json
dnbc4tools/config/cellbarcode/scRNA5Pv1/scRNA_oligo_v1.json
dnbc4tools/config/cellbarcode/scRNAv1HT/scRNA_beads_v1.json
dnbc4tools/config/cellbarcode/scRNAv1HT/scRNA_oligo_v1.json
dnbc4tools/config/cellbarcode/scRNAv2v3HT/scRNA_beads_v2_3.json
dnbc4tools/config/cellbarcode/scRNAv2v3HT/scRNA_oligo_v2_3.json
dnbc4tools/config/cellbarcode/scVDJv1/scVDJ_beads_dark_PE.json
dnbc4tools/config/cellbarcode/scVDJv1/scVDJ_beads_dark_SE.json
dnbc4tools/config/cellbarcode/scVDJv1/scVDJ_beads_v1_PE.json
dnbc4tools/config/cellbarcode/scVDJv1/scVDJ_beads_v1_SE.json
dnbc4tools/config/rna/HCL.ref.csv.gz
dnbc4tools/config/rna/MCA.ref.csv.gz
dnbc4tools/config/rna/adapter.txt
dnbc4tools/config/template/template_scATAC.html
dnbc4tools/config/template/template_scRNA.html
dnbc4tools/config/template/template_scRNA_noanno.html
dnbc4tools/config/template/template_scVDJ_BCR.html
dnbc4tools/config/template/template_scVDJ_TCR.html
dnbc4tools/config/vdj/GRCh38_bcrtcr.fa
DNBC4tools-2.1.2.dist-info/LICENSE
DNBC4tools-2.1.2.dist-info/METADATA
DNBC4tools-2.1.2.dist-info/WHEEL
DNBC4tools-2.1.2.dist-info/entry_points.txt
DNBC4tools-2.1.2.dist-info/top_level.txt
DNBC4tools-2.1.2.dist-info/RECORD
