Metadata-Version: 2.1
Name: DNBC4tools
Version: 2.1.2
Summary: DNBelab Series Single-Cell analysis workflow
Home-page: https://github.com/MGI-tech-bioinformatics/DNBelab_C_Series_HT_scRNA-analysis-software
Author: lishuangshuang3
Author-email: lishuangshuang3@mgi-tech.com
License: MIT
Platform: Linux
License-File: LICENSE
Requires-Dist: polars-lts-cpu (==0.20.2)
Requires-Dist: scanpy[leiden] (==1.9.8)
Requires-Dist: pyranges
Requires-Dist: pyahocorasick (==2.0.0)
Requires-Dist: pysam
Requires-Dist: datatable (==0.11.1)
Requires-Dist: tarjan
Requires-Dist: pyarrow
Requires-Dist: scikit-misc
Requires-Dist: plotly
Requires-Dist: scrublet
Requires-Dist: macs2 (==2.2.9.1)
